binhash/__init__.py
binhash/binhash.py
binhash-0.2.3.dist-info/LICENSE
binhash-0.2.3.dist-info/METADATA
binhash-0.2.3.dist-info/WHEEL
binhash-0.2.3.dist-info/top_level.txt
binhash-0.2.3.dist-info/RECORD
