Metadata-Version: 2.1
Name: binhash
Version: 0.2.3
Summary: Algorithm to compress sparse binary data
Home-page: https://github.com/KarthikRevanuru/binhash
Author: Karthik Revanuru , Raghav Kulkarni , Rameshwar Pratap
Author-email: karthik.revanuru@outlook.com
License: UNKNOWN
Platform: UNKNOWN
Classifier: Programming Language :: Python :: 3
Classifier: License :: OSI Approved :: MIT License
Classifier: Operating System :: OS Independent
